Metadata-Version: 2.1
Name: stbt-extra-stubs
Version: 31.2.1
Summary: Stubs for Stb-tester's premium APIs - NOW RENAMED TO stbt-premium-stubs
Home-page: https://stb-tester.com
Author: Stb-tester.com Ltd.
Author-email: support@stb-tester.com
License: UNKNOWN
Platform: UNKNOWN
Classifier: Development Status :: 5 - Production/Stable
Classifier: Operating System :: OS Independent
Classifier: Programming Language :: Python :: 2.7
Classifier: Programming Language :: Python :: 3.6
Classifier: Topic :: Software Development :: Testing
Requires-Python: >=2.7,!=3.0.*,!=3.1.*,!=3.2.*,!=3.3.*,!=3.4.*,!=3.5.*
